{"chunk_definitions":[{"row":13,"row_count":1,"visible":true,"expansion_state":0,"options":{"engine":"r","label":"unnamed-chunk-102","message":false,"warning":false,"dev":"png"},"document_id":"50FB5E26","chunk_id":"cbs76s6vfnabw","chunk_label":"unnamed-chunk-1"},{"row":20,"row_count":1,"visible":true,"expansion_state":0,"options":{"engine":"r","label":"unnamed-chunk-104","dev":"png"},"document_id":"50FB5E26","chunk_id":"csr8yejwakvft","chunk_label":"unnamed-chunk-2"},{"row":44,"row_count":1,"visible":true,"expansion_state":0,"options":{"engine":"r","label":"unnamed-chunk-107","dev":"png"},"document_id":"50FB5E26","chunk_id":"cpcrqsjz08wrj","chunk_label":"unnamed-chunk-3"},{"row":66,"row_count":1,"visible":true,"expansion_state":0,"options":{"engine":"r","label":"unnamed-chunk-108","dev":"png"},"document_id":"50FB5E26","chunk_id":"crsluryx5vs4k","chunk_label":"unnamed-chunk-4"}],"doc_write_time":1752068756,"chunk_rendered_width":400}